ruspy/__init__.py
ruspy/check_ruspy_dict.py
ruspy/cli.py
ruspy/ruspy_dict.py
ruspy/ruspy_user_dict.py
ruspy/trans_user_dict.py
ruspy/transpiler.py
ruspy_transpiler-0.2.3.dist-info/METADATA
ruspy_transpiler-0.2.3.dist-info/WHEEL
ruspy_transpiler-0.2.3.dist-info/entry_points.txt
ruspy_transpiler-0.2.3.dist-info/top_level.txt
ruspy_transpiler-0.2.3.dist-info/RECORD
