Metadata-Version: 2.4
Name: ruspy-transpiler
Version: 0.2.3
Summary: Транспилятор русского Python: пишите код на русском, получайте стандартный Python!
Author: Саша Трунов
Author-email: Саша Трнуов <shtrnv@ya.ru>
License: MIT
Project-URL: Homepage, https://github.com/c1cada3301-web/ruspy.git
Project-URL: Bug Tracker, https://github.com/c1cada3301-web/ruspy/issues
Keywords: python,transpiler,russian,русский python
Classifier: Programming Language :: Python :: 3
Classifier: License :: OSI Approved :: MIT License
Classifier: Operating System :: OS Independent
Requires-Python: >=3.7
Dynamic: author
Dynamic: requires-python
